dsf_cpp.cpython-310-x86_64-linux-gnu.so
dsf/__init__.py
dsf/bindings.cpp
dsf/dsf.hpp
dsf/base/AdjacencyMatrix.cpp
dsf/base/AdjacencyMatrix.hpp
dsf/base/Dynamics.hpp
dsf/base/Edge.cpp
dsf/base/Edge.hpp
dsf/base/Network.hpp
dsf/base/Node.hpp
dsf/base/SparseMatrix.hpp
dsf/geometry/Point.cpp
dsf/geometry/Point.hpp
dsf/geometry/PolyLine.cpp
dsf/geometry/PolyLine.hpp
dsf/mdt/PointsCluster.cpp
dsf/mdt/PointsCluster.hpp
dsf/mdt/Trajectory.cpp
dsf/mdt/Trajectory.hpp
dsf/mdt/TrajectoryCollection.cpp
dsf/mdt/TrajectoryCollection.hpp
dsf/mobility/Agent.cpp
dsf/mobility/Agent.hpp
dsf/mobility/FirstOrderDynamics.cpp
dsf/mobility/FirstOrderDynamics.hpp
dsf/mobility/Intersection.cpp
dsf/mobility/Intersection.hpp
dsf/mobility/Itinerary.cpp
dsf/mobility/Itinerary.hpp
dsf/mobility/PathCollection.cpp
dsf/mobility/PathCollection.hpp
dsf/mobility/Road.cpp
dsf/mobility/Road.hpp
dsf/mobility/RoadDynamics.hpp
dsf/mobility/RoadJunction.cpp
dsf/mobility/RoadJunction.hpp
dsf/mobility/RoadNetwork.cpp
dsf/mobility/RoadNetwork.hpp
dsf/mobility/Roundabout.cpp
dsf/mobility/Roundabout.hpp
dsf/mobility/Sensors.hpp
dsf/mobility/Station.cpp
dsf/mobility/Station.hpp
dsf/mobility/Street.cpp
dsf/mobility/Street.hpp
dsf/mobility/TrafficLight.cpp
dsf/mobility/TrafficLight.hpp
dsf/python/cartography.py
dsf/utility/Typedef.hpp
dsf/utility/queue.hpp
dsf/utility/TypeTraits/is_node.hpp
dsf/utility/TypeTraits/is_numeric.hpp
dsf/utility/TypeTraits/is_street.hpp
dsf_cpp/__init__.pyi
dsf_cpp/mdt.pyi
dsf_cpp/mobility.pyi
dsf_mobility.libs/libtbb-1e2a936d.so.12.11
dsf_mobility-4.6.1.dist-info/METADATA
dsf_mobility-4.6.1.dist-info/WHEEL
dsf_mobility-4.6.1.dist-info/top_level.txt
dsf_mobility-4.6.1.dist-info/RECORD
dsf_mobility-4.6.1.dist-info/licenses/LICENSE
dsf_mobility-4.6.1.dist-info/sboms/auditwheel.cdx.json
