Metadata-Version: 2.4
Name: dsf-mobility
Version: 4.6.1
Summary: DSF C++ core with Python bindings via pybind11
Home-page: https://github.com/physycom/DynamicalSystemFramework
Author: Grufoony
Author-email: gregorio.berselli@studio.unibo.it
License: CC-BY-NC-SA-4.0
Project-URL: Homepage, https://github.com/physycom/DynamicalSystemFramework
Project-URL: Documentation, https://physycom.github.io/DynamicalSystemFramework/
Project-URL: Repository, https://github.com/physycom/DynamicalSystemFramework
Project-URL: Issues, https://github.com/physycom/DynamicalSystemFramework/issues
Keywords: traffic,simulation,dynamics,network,modeling,transportation,mobility,congestion,flow,optimization
Classifier: Development Status :: 4 - Beta
Classifier: Intended Audience :: Science/Research
Classifier: Intended Audience :: Developers
Classifier: Programming Language :: Python :: 3.10
Classifier: Programming Language :: Python :: 3.12
Classifier: Programming Language :: C++
Classifier: Topic :: Scientific/Engineering :: Physics
Classifier: Topic :: Scientific/Engineering :: Information Analysis
Classifier: Topic :: Software Development :: Libraries :: Python Modules
Classifier: Operating System :: POSIX :: Linux
Classifier: Operating System :: MacOS
Requires-Python: >=3.10
License-File: LICENSE
Requires-Dist: pybind11-stubgen
Requires-Dist: osmnx>=2.0.6
Requires-Dist: networkx>=3
Requires-Dist: numpy
Requires-Dist: geopandas
Requires-Dist: shapely
Dynamic: author
Dynamic: author-email
Dynamic: classifier
Dynamic: description
Dynamic: description-content-type
Dynamic: home-page
Dynamic: keywords
Dynamic: license
Dynamic: license-file
Dynamic: project-url
Dynamic: requires-dist
Dynamic: requires-python
Dynamic: summary
